ttime/__init__.py
ttime/ad_rttc.py
ttime/cheb_tt.py
ttime/f_rttc_helper.py
ttime/numpy_inheritance_helper.py
ttime/pre_cheb_tt.py
ttime/rttc.py
ttime/rttc_helper.py
ttime/tensor.py
ttime/tt.py
ttime/tt_core.py
TTiME-0.0.2.dist-info/LICENSE.txt
TTiME-0.0.2.dist-info/METADATA
TTiME-0.0.2.dist-info/WHEEL
TTiME-0.0.2.dist-info/top_level.txt
TTiME-0.0.2.dist-info/RECORD
