Metadata-Version: 2.1
Name: TTiME
Version: 0.0.2
Summary: Tensor Trains in Mathematics and Engineering
Author: Leonhard X. Driever
Author-email: ttime.python@gmail.com
Classifier: Programming Language :: Python :: 3
Classifier: License :: OSI Approved :: MIT License
Classifier: Operating System :: OS Independent
Requires-Python: >=3.6
License-File: LICENSE.txt
Requires-Dist: coverage
Requires-Dist: numpy
Requires-Dist: tqdm
Requires-Dist: scipy
Requires-Dist: numba
Requires-Dist: setuptools
Requires-Dist: matplotlib
